mkblog/__init__.py
mkblog/plugin.py
mkblog-1.2.0.dist-info/LICENSE
mkblog-1.2.0.dist-info/METADATA
mkblog-1.2.0.dist-info/WHEEL
mkblog-1.2.0.dist-info/entry_points.txt
mkblog-1.2.0.dist-info/top_level.txt
mkblog-1.2.0.dist-info/RECORD
