Metadata-Version: 2.1
Name: mkblog
Version: 1.2.0
Summary: MkDocs plugin for blogging
Home-page: https://github.com/derJD/python-mkblog
Author: Jean-Denis Gebhardt
Author-email: projects@der-jd.de
License: MIT
Platform: UNKNOWN
Classifier: Environment :: Console
Classifier: Intended Audience :: System Administrators
Classifier: Operating System :: OS Independent
Classifier: Programming Language :: Python :: 3 :: Only
Classifier: Programming Language :: Python :: 3.6
Classifier: Programming Language :: Python :: 3.7
Classifier: Programming Language :: Python :: 3.8
Classifier: Programming Language :: Python :: 3.9
Classifier: License :: OSI Approved :: MIT License
Classifier: Topic :: System :: Systems Administration
Classifier: Topic :: Utilities
Requires-Python: >=3.6
Requires-Dist: mkdocs (>=1)
Requires-Dist: mkdocs-awesome-pages-plugin
Requires-Dist: mkdocs-material
Requires-Dist: GitPython
